cyr/__init__.py
cyr/cyr.py
cyr-0.0.1.data/data/share/man/man1/cyr.1
cyr-0.0.1.dist-info/LICENSE
cyr-0.0.1.dist-info/METADATA
cyr-0.0.1.dist-info/WHEEL
cyr-0.0.1.dist-info/entry_points.txt
cyr-0.0.1.dist-info/top_level.txt
cyr-0.0.1.dist-info/RECORD
