Metadata-Version: 2.1
Name: cyr
Version: 0.0.1
Summary: smart ascii to unicode cyrillic converter
Home-page: https://github.com/Aleksej10/cyrillic
Author: Aleksej
Author-email: mr.strale@gmain.com
License: UNKNOWN
Keywords: cyrillic converter
Platform: UNKNOWN
Classifier: Programming Language :: Python :: 3
Classifier: License :: OSI Approved :: MIT License
Classifier: Operating System :: POSIX :: Linux
Requires-Python: >=3.6
Requires-Dist: numpy
Requires-Dist: torch
